scoly_api/__init__.py
scoly_api/client.py
matildapeak_scoly_api-1.0.1.dist-info/METADATA
matildapeak_scoly_api-1.0.1.dist-info/WHEEL
matildapeak_scoly_api-1.0.1.dist-info/RECORD
