Metadata-Version: 2.1
Name: matildapeak-scoly-api
Version: 1.0.1
Summary: The Scoly API Package
Author: Alan Christie
Author-email: alan.christie@matildapeak.com
Requires-Python: >=3.8
Classifier: Programming Language :: Python :: 3
Classifier: Programming Language :: Python :: 3.8
Classifier: Programming Language :: Python :: 3.9
Classifier: Programming Language :: Python :: 3.10
Classifier: Programming Language :: Python :: 3.11
Requires-Dist: requests (>=2)
